proxy_random/__init__.py
proxy_random/config.py
proxy_random/extract.py
proxy_random/provider.py
proxy_random/proxy.py
proxy_random/query.py
proxy_random/random_proxy.py
proxy_random/utils.py
proxy_random-0.0.2.dist-info/LICENSE
proxy_random-0.0.2.dist-info/METADATA
proxy_random-0.0.2.dist-info/WHEEL
proxy_random-0.0.2.dist-info/top_level.txt
proxy_random-0.0.2.dist-info/RECORD
