Metadata-Version: 2.1
Name: proxy-random
Version: 0.0.2
Summary: A simple package to get random proxy from online proxylist sites.
Author: AmirMohammad
Author-email: amirmohammad@duck.com
License: UNKNOWN
Platform: UNKNOWN
Classifier: Programming Language :: Python :: 3
Classifier: License :: OSI Approved :: MIT License
Classifier: Operating System :: OS Independent
Requires-Python: >=3.7
License-File: LICENSE
Requires-Dist: aiohttp
Requires-Dist: aiohttp-proxy
Requires-Dist: beautifulsoup4
